appsync_ws_client/__init__.py
appsync_ws_client/client.py
appsync_ws_client/exceptions.py
tests/__init__.py
tests/test_appsync_ws_client.py
appsync_ws_client-0.1.3.dist-info/LICENSE
appsync_ws_client-0.1.3.dist-info/METADATA
appsync_ws_client-0.1.3.dist-info/WHEEL
appsync_ws_client-0.1.3.dist-info/top_level.txt
appsync_ws_client-0.1.3.dist-info/RECORD
