Metadata-Version: 2.1
Name: appsync-ws-client
Version: 0.1.3
Summary: A package for connecting to AWS AppSync WebSocket API using graphql subscriptions
Home-page: https://github.com/dhinesh03/python-appsync-ws-client
Author: Dhinesh Kumar Sundaram
Author-email: dhinesh.gs@gmail.com
Classifier: Programming Language :: Python :: 3
Classifier: License :: OSI Approved :: MIT License
Classifier: Operating System :: OS Independent
Requires-Python: >=3.9
License-File: LICENSE
Requires-Dist: websocket-client
